agentman/__init__.py
agentman/__main__.py
agentman/agent_builder.py
agentman/agentfile_parser.py
agentman/cli.py
agentman/common.py
agentman/version.py
agentman_mcp-0.1.6.dist-info/licenses/LICENSE
agentman_mcp-0.1.6.dist-info/METADATA
agentman_mcp-0.1.6.dist-info/WHEEL
agentman_mcp-0.1.6.dist-info/entry_points.txt
agentman_mcp-0.1.6.dist-info/top_level.txt
agentman_mcp-0.1.6.dist-info/RECORD
