Metadata-Version: 2.4
Name: agentman-mcp
Version: 0.1.6
Summary: A tool for building and managing AI agents
Author-email: Xiaodong Ye <yeahdongcn@gmail.com>
Maintainer-email: Xiaodong Ye <yeahdongcn@gmail.com>
License-Expression: MIT
Project-URL: Homepage, https://github.com/yeahdongcn/agentman
Project-URL: Documentation, https://github.com/yeahdongcn/agentman#readme
Project-URL: Repository, https://github.com/yeahdongcn/agentman.git
Project-URL: Issues, https://github.com/yeahdongcn/agentman/issues
Project-URL: Changelog, https://github.com/yeahdongcn/agentman/releases
Keywords: ai,agents,mcp,model-context-protocol,docker,containerization,automation
Classifier: Development Status :: 4 - Beta
Classifier: Intended Audience :: Developers
Classifier: Intended Audience :: Information Technology
Classifier: Operating System :: OS Independent
Classifier: Programming Language :: Python :: 3
Classifier: Programming Language :: Python :: 3.10
Classifier: Programming Language :: Python :: 3.11
Classifier: Programming Language :: Python :: 3.12
Classifier: Programming Language :: Python :: 3.13
Classifier: Topic :: Software Development :: Libraries :: Python Modules
Classifier: Topic :: Scientific/Engineering :: Artificial Intelligence
Classifier: Topic :: System :: Systems Administration
Classifier: Topic :: Utilities
Requires-Python: >=3.10
License-File: LICENSE
Requires-Dist: fast-agent-mcp>=0.2.33
Provides-Extra: dev
Requires-Dist: black>=25.1.0; extra == "dev"
Requires-Dist: isort>=6.0.1; extra == "dev"
Requires-Dist: pytest>=8.0.0; extra == "dev"
Requires-Dist: pytest-cov>=4.0.0; extra == "dev"
Requires-Dist: pylint>=3.0.0; extra == "dev"
Provides-Extra: publish
Requires-Dist: build>=1.0.0; extra == "publish"
Requires-Dist: twine>=5.0.0; extra == "publish"
Dynamic: license-file
